serpynt/__init__.py
serpynt-0.0.1.dist-info/licenses/LICENSE
serpynt-0.0.1.dist-info/METADATA
serpynt-0.0.1.dist-info/WHEEL
serpynt-0.0.1.dist-info/top_level.txt
serpynt-0.0.1.dist-info/RECORD
