Metadata-Version: 2.4
Name: serpynt
Version: 0.0.1
Summary: A minimal Python static site generator (SSG).
Author-email: "Tyler W. Phass" <codezealot+dev@pm.me>
License: MIT License
Requires-Python: >=3.8
License-File: LICENSE
Dynamic: license-file
